slim/__init__.py
slim/example_gp.py
slim/example_gsgp.py
slim/example_slim.py
slim/main_gp.py
slim/main_gsgp.py
slim/main_slim.py
slim/algorithms/__init__.py
slim/algorithms/GP/__init__.py
slim/algorithms/GP/gp.py
slim/algorithms/GP/operators/__init__.py
slim/algorithms/GP/operators/crossover_operators.py
slim/algorithms/GP/operators/mutators.py
slim/algorithms/GP/representations/__init__.py
slim/algorithms/GP/representations/population.py
slim/algorithms/GP/representations/tree.py
slim/algorithms/GP/representations/tree_utils.py
slim/algorithms/GSGP/__init__.py
slim/algorithms/GSGP/gsgp.py
slim/algorithms/GSGP/operators/__init__.py
slim/algorithms/GSGP/operators/crossover_operators.py
slim/algorithms/GSGP/operators/mutators.py
slim/algorithms/GSGP/representations/__init__.py
slim/algorithms/GSGP/representations/population.py
slim/algorithms/GSGP/representations/tree.py
slim/algorithms/GSGP/representations/tree_utils.py
slim/algorithms/SLIM_GSGP/__init__.py
slim/algorithms/SLIM_GSGP/slim_gsgp.py
slim/algorithms/SLIM_GSGP/operators/__init__.py
slim/algorithms/SLIM_GSGP/operators/mutators.py
slim/algorithms/SLIM_GSGP/representations/__init__.py
slim/algorithms/SLIM_GSGP/representations/individual.py
slim/algorithms/SLIM_GSGP/representations/population.py
slim/config/__init__.py
slim/config/gp_config.py
slim/config/gsgp_config.py
slim/config/slim_config.py
slim/datasets/__init__.py
slim/datasets/data_loader.py
slim/datasets/__pycache__/__init__.cpython-310.pyc
slim/datasets/__pycache__/data_loader.cpython-310.pyc
slim/datasets/data/airfoil.txt
slim/datasets/data/bike_sharing_day.txt
slim/datasets/data/bioavailability.txt
slim/datasets/data/boston.txt
slim/datasets/data/breast_cancer.txt
slim/datasets/data/concrete_slump.txt
slim/datasets/data/concrete_strength.txt
slim/datasets/data/diabetes.txt
slim/datasets/data/efficiency_cooling.txt
slim/datasets/data/efficiency_heating.txt
slim/datasets/data/forest_fires.txt
slim/datasets/data/ld50.txt
gsgp_slim-0.1.9.dist-info/LICENSE
gsgp_slim-0.1.9.dist-info/METADATA
gsgp_slim-0.1.9.dist-info/WHEEL
gsgp_slim-0.1.9.dist-info/top_level.txt
gsgp_slim-0.1.9.dist-info/RECORD
